docrouter_sdk/__init__.py
docrouter_sdk/client.py
docrouter_sdk/documents.py
docrouter_sdk/llm.py
docrouter_sdk/ocr.py
docrouter_sdk/prompts.py
docrouter_sdk/py.typed
docrouter_sdk/schemas.py
docrouter_sdk/tags.py
docrouter_sdk/models/__init__.py
docrouter_sdk/models/document.py
docrouter_sdk/models/llm.py
docrouter_sdk/models/ocr.py
docrouter_sdk/models/prompt.py
docrouter_sdk/models/schema.py
docrouter_sdk/models/tag.py
docrouter_sdk-0.1.5.dist-info/METADATA
docrouter_sdk-0.1.5.dist-info/WHEEL
docrouter_sdk-0.1.5.dist-info/RECORD
