Metadata-Version: 2.4
Name: docrouter-sdk
Version: 0.1.5
Summary: SDK for interacting with the DocRouter API
Project-URL: Repository, https://github.com/analytiq/doc-router
Author: Analytiq
License: Apache-2.0
Requires-Python: >=3.8
Requires-Dist: pydantic>=2.0.0
Requires-Dist: requests>=2.31.0
